yagls/__init__.py
yagls/__main__.py
yagls/generator.py
yagls/yagls.py
yagls-1.4.0.dist-info/LICENSE
yagls-1.4.0.dist-info/WHEEL
yagls-1.4.0.dist-info/METADATA
yagls-1.4.0.dist-info/RECORD
