Metadata-Version: 2.1
Name: yagls
Version: 1.4.0
Summary: Yet Another Github Label Synchroniser
Home-page: https://github.com/github-labels/yagls
License: MIT
Author: preeded
Author-email: 86511859+preeded@users.noreply.github.com
Maintainer: preeded
Maintainer-email: 86511859+preeded@users.noreply.github.com
Requires-Python: >=3.10,<4.0
Classifier: License :: OSI Approved :: MIT License
Classifier: Programming Language :: Python :: 3
Classifier: Programming Language :: Python :: 3.10
Requires-Dist: aiohttp
Project-URL: Repository, https://github.com/github-labels/yagls
